pdm_una/__init__.py
pdm_una/hook.py
pdm_una/include.py
pdm_una/meta.py
pdm_una/py.typed
pdm_una/util.py
pdm_una-0.4.0.dist-info/METADATA
pdm_una-0.4.0.dist-info/WHEEL
pdm_una-0.4.0.dist-info/entry_points.txt
pdm_una-0.4.0.dist-info/RECORD
