Metadata-Version: 2.3
Name: pdm-una
Version: 0.4.0
Summary: Python monorepo tooling
Project-URL: homepage, https://github.com/carderne/una
Project-URL: repository, https://github.com/carderne/una
Author-email: Chris Arderne <chris@rdrn.me>
License: MIT License
Keywords: build,monorepo,pdm,python,uv
Classifier: Environment :: Console
Classifier: Intended Audience :: Developers
Classifier: License :: OSI Approved :: MIT License
Classifier: Operating System :: Unix
Classifier: Programming Language :: Python
Classifier: Programming Language :: Python :: 3.10
Classifier: Programming Language :: Python :: 3.11
Classifier: Programming Language :: Python :: 3.12
Requires-Python: >=3.11
Requires-Dist: pdm-backend
